tohu/__init__.py
tohu/_version.py
tohu/v4/base.py
tohu/v4/custom_generator.py
tohu/v4/derived_generators.py
tohu/v4/dispatch_generators.py
tohu/v4/item_list.py
tohu/v4/logging.py
tohu/v4/primitive_generators.py
tohu/v4/set_special_methods.py
tohu/v4/spawn_context.py
tohu/v4/utils.py
tohu/v6/__init__.py
tohu/v6/base.py
tohu/v6/custom_generator_OLD.py
tohu/v6/derived_generators.py
tohu/v6/generator_dispatch.py
tohu/v6/item_list.py
tohu/v6/logging.py
tohu/v6/primitive_generators.py
tohu/v6/set_special_methods.py
tohu/v6/spawn_mapping.py
tohu/v6/tohu_namespace.py
tohu/v6/utils.py
tohu/v6/custom_generator/__init__.py
tohu/v6/custom_generator/custom_generator.py
tohu/v6/custom_generator/utils.py
tohu-0.6.7.dist-info/LICENSE
tohu-0.6.7.dist-info/METADATA
tohu-0.6.7.dist-info/WHEEL
tohu-0.6.7.dist-info/top_level.txt
tohu-0.6.7.dist-info/RECORD
