Metadata-Version: 2.1
Name: tohu
Version: 0.6.7
Summary: Create random data in a controllable way
Home-page: https://github.com/maxalbert/tohu
Author: Maximilian Albert
Author-email: maximilian.albert@gmail.com
License: MIT
Platform: UNKNOWN
Classifier: Development Status :: 4 - Beta
Classifier: Intended Audience :: Developers
Classifier: Topic :: Software Development :: Quality Assurance
Classifier: Topic :: Software Development :: Testing
Classifier: Topic :: Utilities
Classifier: License :: OSI Approved :: MIT License
Classifier: Programming Language :: Python :: 3
Classifier: Programming Language :: Python :: 3.6
Requires-Dist: attrs
Requires-Dist: bidict
Requires-Dist: faker
Requires-Dist: geojson
Requires-Dist: pandas
Requires-Dist: psycopg2-binary
Requires-Dist: shapely
Requires-Dist: sqlalchemy
Requires-Dist: tqdm
Provides-Extra: dev
Requires-Dist: ipython ; extra == 'dev'
Requires-Dist: jupyter ; extra == 'dev'
Provides-Extra: test
Requires-Dist: pytest ; extra == 'test'
Requires-Dist: nbval ; extra == 'test'
